ran_redis_lock/__init__.py
ran_redis_lock/lock.py
ran_redis_lock-0.0.5.dist-info/LICENSE
ran_redis_lock-0.0.5.dist-info/METADATA
ran_redis_lock-0.0.5.dist-info/WHEEL
ran_redis_lock-0.0.5.dist-info/top_level.txt
ran_redis_lock-0.0.5.dist-info/RECORD
